js_asset/__init__.py
js_asset/context_processors.py
js_asset/js.py
django_js_asset-3.1.1.dist-info/METADATA
django_js_asset-3.1.1.dist-info/WHEEL
django_js_asset-3.1.1.dist-info/licenses/LICENSE
django_js_asset-3.1.1.dist-info/RECORD
